nececv/Universe.py
nececv/__init__.py
nececv/nececv.py
nececv/tempCodeRunnerFile.py
nececv-0.2.5.dist-info/licenses/LICENSE
nececv-0.2.5.dist-info/METADATA
nececv-0.2.5.dist-info/WHEEL
nececv-0.2.5.dist-info/top_level.txt
nececv-0.2.5.dist-info/RECORD
